cruscoplanets_gui/__init__.py
cruscoplanets_gui/__main__.py
cruscoplanets_gui/config.py
cruscoplanets_gui/main_window.py
cruscoplanets_gui/resources.py
cruscoplanets_gui/about/en.md
cruscoplanets_gui/about/it.md
cruscoplanets_gui/config/base.txt
cruscoplanets_gui/databases/__init__.py
cruscoplanets_gui/databases/database_filters.py
cruscoplanets_gui/databases/database_models.py
cruscoplanets_gui/databases/database_views.py
cruscoplanets_gui/databases/delegates.py
cruscoplanets_gui/databases/resizable_grid.py
cruscoplanets_gui/main_window_widgets/__init__.py
cruscoplanets_gui/main_window_widgets/chart.py
cruscoplanets_gui/main_window_widgets/chart_form.py
cruscoplanets_gui/main_window_widgets/datetime_formatter.py
cruscoplanets_gui/main_window_widgets/event_form.py
cruscoplanets_gui/main_window_widgets/location_searcher.py
cruscoplanets_gui/main_window_widgets/personal_data_form.py
cruscoplanets_gui/main_window_widgets/svg_widget.py
cruscoplanets_gui/settings/__init__.py
cruscoplanets_gui/settings/language_settings_form.py
cruscoplanets_gui/settings/settings_form.py
cruscoplanets_gui-0.0.5.dist-info/COPYING
cruscoplanets_gui-0.0.5.dist-info/METADATA
cruscoplanets_gui-0.0.5.dist-info/WHEEL
cruscoplanets_gui-0.0.5.dist-info/entry_points.txt
cruscoplanets_gui-0.0.5.dist-info/top_level.txt
cruscoplanets_gui-0.0.5.dist-info/RECORD
