Metadata-Version: 2.1
Name: cruscoplanets-gui
Version: 0.0.5
Summary: GUI interface for the cruscoplanets package
Home-page: https://gitlab.com/kikulacho92/cruscoplanets_gui
Author: Emiliano Minerba
Author-email: emi.nerba@gmail.com
License: GPL
Keywords: astrology Morpurgo dialectic charts
Platform: UNKNOWN
Requires-Python: ==3.8.10
Requires-Dist: PyQt5 (==5.15.4)
Requires-Dist: cruscoplanets (>=0.3.1)
Requires-Dist: langcodes[data]
Requires-Dist: pycountry (==22.3.5)
Requires-Dist: wheel
